{
  "cases": [
    {
      "id" :"bbfbb752-9dae-48e4-a69d-f132998f737d",
      "urn": "POL5809338539",
      "firstName": "Hakan",
      "lastName": "Kurtulus",
      "pleaDate": "2018-03-20T18:14:29.894Z",
      "prosecutingAuthority": "West Yorkshire Police"
    },
    {
      "id" :"bbfbb752-9dae-48e4-a69d-f132998f737e",
      "urn": "TFL7631646",
      "firstName": "Hakan",
      "lastName": "Kurtulus",
      "pleaDate": "2018-03-20T18:14:29.894Z",
      "prosecutingAuthority": "Transport for London"
    }
  ],
  "results": 121,
  "pageCount": 11
}
