{
  "$schema": "http://json-schema.org/draft-04/schema#",
  "id": "http://justice.gov.uk/json/schemas/domains/sjp/command/sjp.record-case-adjourned-to-later-sjp-hearing.json",
  "type": "object",
  "properties": {
    "caseId": {
      "$ref": "http://justice.gov.uk/domain/core/common/definitions.json#/definitions/uuid"
    },
    "sjpSessionId": {
      "$ref": "http://justice.gov.uk/domain/core/common/definitions.json#/definitions/uuid"
    },
    "adjournedTo": {
      "$ref": "http://justice.gov.uk/json/schemas/domains/sjp/temporal.json#/definitions/date"
    }
  },
  "required": [
    "caseId",
    "sjpSessionId",
    "adjournedTo"
  ],
  "additionalProperties": false
}
